pytest_testobject.py
pytest_testobject-1.0.0.dist-info/LICENSE
pytest_testobject-1.0.0.dist-info/METADATA
pytest_testobject-1.0.0.dist-info/WHEEL
pytest_testobject-1.0.0.dist-info/entry_points.txt
pytest_testobject-1.0.0.dist-info/top_level.txt
pytest_testobject-1.0.0.dist-info/RECORD
