Metadata-Version: 2.1
Name: pytest-testobject
Version: 1.0.0
Summary: Plugin to use TestObject Suites with Pytest
Home-page: https://github.com/enriquegh/pytest-testobject
Author: Enrique Gonzalez
Author-email: egonzalezh94@gmail.com
Maintainer: Enrique Gonzalez
Maintainer-email: egonzalezh94@gmail.com
License: MIT
Platform: UNKNOWN
Classifier: Development Status :: 4 - Beta
Classifier: Framework :: Pytest
Classifier: Intended Audience :: Developers
Classifier: Topic :: Software Development :: Testing
Classifier: Programming Language :: Python
Classifier: Programming Language :: Python :: 3
Classifier: Programming Language :: Python :: 3.3
Classifier: Programming Language :: Python :: 3.5
Classifier: Programming Language :: Python :: Implementation :: CPython
Classifier: Programming Language :: Python :: Implementation :: PyPy
Classifier: Operating System :: OS Independent
Classifier: License :: OSI Approved :: MIT License
Requires-Python: >=3.5
Requires-Dist: pytest (>=3.1.1)
Requires-Dist: Appium-Python-Client
Requires-Dist: testobject (>=0.3.0)
